{
  "workbench.iconTheme": "material-icon-theme",
  "editor.defaultFormatter": "esbenp.prettier-vscode",
  "notebook.defaultFormatter": "esbenp.prettier-vscode",
  "editor.formatOnSave": true,
  "emmet.triggerExpansionOnTab": true,
  "emmet.variables": {
    "lang": "ja"
  },
  "emmet.includeLanguages": {
    "javascript": "javascriptreact"
  },
  "emmet.syntaxProfiles": {
    "html": {
      "filters": "html,c"
    }
  },
  "git.suggestSmartCommit": false,
  "codeium.enableConfig": {
    "*": true
  },
  "editor.codeActionsOnSave": {
    "source.addMissingImports": "explicit",
    "source.organizeImports": "explicit"
  }
}
